inspector_mils/__init__.py
inspector_mils/inspector.py
inspector_mils-0.0.1.dist-info/LICENSE
inspector_mils-0.0.1.dist-info/METADATA
inspector_mils-0.0.1.dist-info/WHEEL
inspector_mils-0.0.1.dist-info/top_level.txt
inspector_mils-0.0.1.dist-info/RECORD
