Metadata-Version: 2.1
Name: inspector-mils
Version: 0.0.1
Summary: A decorator that inspects functions. Logs function name, args and kwargs.
Author-email: Jay Milagroso <j.milagroso@gmail.com>
Classifier: Programming Language :: Python :: 3
Classifier: License :: OSI Approved :: MIT License
Classifier: Operating System :: OS Independent
Requires-Python: >=3.6
License-File: LICENSE
